Metadata-Version: 2.1
Name: SimpleSpider
Version: 0.0.6
Summary: easier for you to use internet spider
Home-page: https://github.com/shanzhengliu/SimpleSpider
Author: shanzhengliu
Author-email: liushanzheng960522@outlook.com
License: UNKNOWN
Platform: UNKNOWN
Classifier: Programming Language :: Python :: 3
Classifier: License :: OSI Approved :: MIT License
Classifier: Operating System :: OS Independent
